tdcsophiread/__init__.py
tdcsophiread/_core.cpython-312-x86_64-linux-gnu.so
tdcsophiread/_version.py
tdcsophiread/analysis.py
tdcsophiread/config.py
tdcsophiread/cli/__init__.py
tdcsophiread/cli/auto_reducer.py
tdcsophiread/cli/config_validator.py
tdcsophiread/cli/main.py
tdcsophiread.libs/libtbb-9f9da21c.so.12.4
tdcsophiread-3.1.3.dist-info/METADATA
tdcsophiread-3.1.3.dist-info/WHEEL
tdcsophiread-3.1.3.dist-info/entry_points.txt
tdcsophiread-3.1.3.dist-info/RECORD
tdcsophiread-3.1.3.dist-info/licenses/LICENSE
