Metadata-Version: 2.2
Name: tdcsophiread
Version: 3.1.3
Summary: High-performance TDC-only TPX3 neutron imaging data processor
Keywords: neutron imaging,timepix3,tpx3,tdc,time-of-flight,detector,high-performance,scientific computing
Author-Email: Chen Zhang <zhangc@ornl.gov>, ORNL Neutron Imaging Team <neutronimaging@ornl.gov>
Maintainer-Email: Chen Zhang <zhangc@ornl.gov>
License: GPL-3.0-or-later
Classifier: Development Status :: 4 - Beta
Classifier: Intended Audience :: Science/Research
Classifier: Topic :: Scientific/Engineering :: Physics
Classifier: Topic :: Scientific/Engineering :: Image Processing
Classifier: License :: OSI Approved :: GNU General Public License v3 or later (GPLv3+)
Classifier: Programming Language :: Python :: 3
Classifier: Programming Language :: Python :: 3.10
Classifier: Programming Language :: Python :: 3.11
Classifier: Programming Language :: Python :: 3.12
Classifier: Programming Language :: Python :: 3.13
Classifier: Programming Language :: Python :: 3.14
Classifier: Programming Language :: C++
Classifier: Operating System :: POSIX :: Linux
Classifier: Operating System :: MacOS
Classifier: Operating System :: Microsoft :: Windows
Project-URL: Homepage, https://github.com/ornlneutronimaging/mcpevent2hist
Project-URL: Documentation, https://github.com/ornlneutronimaging/mcpevent2hist/blob/main/README.md
Project-URL: Repository, https://github.com/ornlneutronimaging/mcpevent2hist.git
Project-URL: Issues, https://github.com/ornlneutronimaging/mcpevent2hist/issues
Project-URL: Changelog, https://github.com/ornlneutronimaging/mcpevent2hist/blob/main/CHANGELOG.md
Requires-Python: >=3.10
Requires-Dist: numpy>=2.1.0
Requires-Dist: h5py>=3.12.0
Requires-Dist: pydantic>=2.11.7
Requires-Dist: matplotlib>=3.10.3
Requires-Dist: tifffile>=2024.1.18
Provides-Extra: dev
Requires-Dist: pytest>=7.0.0; extra == "dev"
Requires-Dist: pytest-cov; extra == "dev"
Requires-Dist: pytest-benchmark; extra == "dev"
Requires-Dist: black; extra == "dev"
Requires-Dist: isort; extra == "dev"
Requires-Dist: mypy; extra == "dev"
Requires-Dist: pre-commit>=4.2.0; extra == "dev"
Requires-Dist: sphinx; extra == "dev"
Requires-Dist: sphinx-rtd-theme; extra == "dev"
Requires-Dist: myst-parser; extra == "dev"
Provides-Extra: all
Requires-Dist: tdcsophiread[dev]; extra == "all"
